{
 "slides":[
        {
      "slide_number": 53,
      "title": "المبنيات في كلام العرب",
      "blocks": [
        {
          "type": "heading",
          "data": "1- الأسماء المبنية"
        },
        {
          "type": "text",
          "data": "الضَّمَائِر: أنا، أنتَ، هو، هي، نحن، أنتم، هم..."
        }
      ]
    },
    {
      "slide_number": 54,
      "title": "المبنيات في كلام العرب",
      "blocks": [
        {
          "type": "heading",
          "data": "1- الأسماء المبنية"
        },
        {
          "type": "text",
          "data": "أَسْمَاءُ الْإِشَارَةِ سِوَى الْمُثَنَّى منها وهي: (هذان وهذين، وهاتان، وهاتين). فهي معربة وتعامل معالمة المثنى كما سيأتي."
        }
      ]
    },
    {
      "slide_number": 55,
      "title": "المبنيات في كلام العرب",
      "blocks": [
        {
          "type": "heading",
          "data": "1- الأسماء المبنية"
        },
        {
          "type": "text",
          "data": "الْأَسْمَاءُ الْمَوْصُولَةُ سِوَى الْمُثَنَّى منها وهي: (اللذان واللذين، واللتان، واللتين). فمعربة وتعامل معالمة المثنى كما سيأتي."
        }
      ]
    },
    {
      "slide_number": 56,
      "title": "المبنيات في كلام العرب",
      "blocks": [
        {
          "type": "heading",
          "data": "1- الأسماء المبنية"
        },
        {
          "type": "text",
          "data": "أَسْمَاءُ الِاسْتِفْهَامِ عَدَا (أَيَّ).  وهي أدوات يؤتى بها للسؤال والاستفهام. مثل: مَنْ، كيفَ، أينَ. وجميع أدوات الاستفهام أسماء إلا الهمزة وهل"
        }
      ]
    },
    {
      "slide_number": 57,
      "title": "المبنيات في كلام العرب",
      "blocks": [
        {
          "type": "heading",
          "data": "1- الأسماء المبنية"
        },
        {
          "type": "text",
          "data": "أَسْمَاءُ الشَّرْطِ عَدَا (أَيَّ). وهي أدوات يؤتى بها للربط بين فعل الشرط وجوابه. مثل: ما، إذا، مهما"
        }
      ]
    },
    {
      "slide_number": 58,
      "title": "المبنيات في كلام العرب",
      "blocks": [
        {
          "type": "heading",
          "data": "1- الأسماء المبنية"
        },
        {
          "type": "text",
          "data": "أَسْمَاءُ الْأَفْعَالِ، وهي كلمات تنوب عن الفعل في المعنى والعمل، ولا تقبل علاماته. نَحْوُ : صَه، وَآمِينَ، وَهَيْهَاتَ، وَشَتَّانَ، وَأُفٌ، وَوَيْ."
        }
      ]
    },
    {
      "slide_number": 59,
      "title": "المبنيات في كلام العرب",
      "blocks": [
        {
          "type": "heading",
          "data": "1- الأسماء المبنية"
        },
        {
          "type": "text",
          "data": "الْعَلَمُ الْمَخْتُومُ بِــ(وَيْهِ)، يبنى على الكسر نَحْوُ : سِيبَوَيْهِ، راهويهِ."
        }
      ]
    },
    {
      "slide_number": 60,
      "title": "المبنيات في كلام العرب",
      "blocks": [
        {
          "type": "heading",
          "data": "1- الأسماء المبنية"
        },
        {
          "type": "text",
          "data": "الْأَعْدَادُ الْمُرَكَّبَةُ عَذَا اثْنَيْ عَشَرَ. فيعامل معاملة المثنى. وتبنى الأعداد المركبة على فتح الجزأين مثل: جاء أحدَ عشرَ طالبًا (وإني رأيت أحدَ عشرَ كوكبًا) وجلست مع أحدَ عشرَ طالبً."
        }
      ]
    },
    {
      "slide_number": 61,
      "title": "المبنيات في كلام العرب",
      "blocks": [
        {
          "type": "heading",
          "data": "1- الأسماء المبنية"
        },
        {
          "type": "text",
          "data": "الظُّرُوفُ الْمُرَكَّبَةُ، وهي المكونة من كلمين تدلان باجتماعهما على زمان واحد. وتبنى على الفتح. نَحْوُ : ذكرت اللهَ لَيْلَ نَهَارَ، وَصَبَاحَ مَسَاءً."
        }
      ]
    },
    {
      "slide_number": 62,
      "title": "المبنيات في كلام العرب",
      "blocks": [
        {
          "type": "heading",
          "data": "1- الأسماء المبنية"
        },
        {
          "type": "text",
          "data": "بعض الظروف المفردة وهي: (إذ، إذا, أمسِ، الآنَ، منذُ مذْ، قطُ، بينَ وبينما ريثَ وريثما، لمّا، حيثُ، هنا، ثَمَّ، أينَ)"
        }
      ]
    },
    {
      "slide_number": 63,
      "title": "المبنيات في كلام العرب",
      "blocks": [
        {
          "type": "heading",
          "data": "1- الأسماء المبنية"
        },
        {
          "type": "text",
          "data": "المنادى المفرد، اسم لا النافية للجنس المفرد"
        }
      ]
    }
 ]       

}